typeschema/__init__.py
typeschema/decorators.py
typeschema/typeschema.py
typeschema/properties/__init__.py
typeschema/properties/location.py
typeschema/properties/network.py
typeschema/properties/time.py
typeschema/types/__init__.py
typeschema/types/location.py
typeschema/types/network.py
typeschema/types/time.py
typeschema-0.0.2.dist-info/DESCRIPTION.rst
typeschema-0.0.2.dist-info/METADATA
typeschema-0.0.2.dist-info/metadata.json
typeschema-0.0.2.dist-info/RECORD
typeschema-0.0.2.dist-info/top_level.txt
typeschema-0.0.2.dist-info/WHEEL
