Metadata-Version: 2.0
Name: typeschema
Version: 0.0.2
Summary: UNKNOWN
Home-page: https://github.com/tyba/typeschema
Author: Tyba
Author-email: development@tyba.com
License: MIT
Platform: UNKNOWN
Classifier: Development Status :: 3 - Alpha
Classifier: Intended Audience :: Developers
Classifier: Topic :: Software Development :: Libraries
Classifier: License :: OSI Approved :: MIT License
Classifier: Programming Language :: Python :: 2
Classifier: Programming Language :: Python :: 2.6
Classifier: Programming Language :: Python :: 2.7
Requires-Dist: jsonschema (==2.4.0)
Requires-Dist: incf.countryutils (==1.0)
